louis_ri/__init__.py
louis_ri/calcule_RI.py
louis_ri-0.0.1.dist-info/METADATA
louis_ri-0.0.1.dist-info/WHEEL
louis_ri-0.0.1.dist-info/licenses/LICENSE
louis_ri-0.0.1.dist-info/RECORD
