Metadata-Version: 2.1
Name: louis_ri
Version: 0.0.1
Summary: Louis Genieys's IR toolbox
Project-URL: Homepage, https://github.com/louisgenie/louis_ri
Project-URL: Bug Tracker, https://github.com/louisgenie/louis_ri/issues
Author-email: Louis Genieys <lgenieys@gmail.com>
License: Copyright (c) 2018 The Python Packaging Authority
License-File: LICENSE
Classifier: License :: OSI Approved :: MIT License
Classifier: Operating System :: OS Independent
Classifier: Programming Language :: Python :: 3
Requires-Python: >=3.7
